{"nodes": [{"id": "home_naschpitz_projects_nn_ann_ann_corecpu_hpp", "label": "ANN_CoreCPU.hpp", "file_type": "code", "source_file": "ANN/ANN_CoreCPU.hpp", "source_location": "L1"}, {"id": "ann_ann_corecpu_corecpu", "label": "CoreCPU", "file_type": "code", "source_file": "ANN/ANN_CoreCPU.hpp", "source_location": "L20"}, {"id": "core", "label": "Core", "file_type": "code", "source_file": "", "source_location": ""}, {"id": "ann_ann_corecpu_corecpu_predict", "label": "predict", "file_type": "code", "source_file": "ANN/ANN_CoreCPU.hpp", "source_location": "L27"}, {"id": "ann_ann_corecpu_corecpu_train", "label": "train", "file_type": "code", "source_file": "ANN/ANN_CoreCPU.hpp", "source_location": "L29"}, {"id": "ann_ann_corecpu_corecpu_test", "label": "test", "file_type": "code", "source_file": "ANN/ANN_CoreCPU.hpp", "source_location": "L30"}, {"id": "ann_ann_corecpu_corecpu_backpropagate", "label": "backpropagate", "file_type": "code", "source_file": "ANN/ANN_CoreCPU.hpp", "source_location": "L33"}, {"id": "ann_ann_corecpu_corecpu_accumulate", "label": "accumulate", "file_type": "code", "source_file": "ANN/ANN_CoreCPU.hpp", "source_location": "L34"}, {"id": "ann_ann_corecpu_corecpu_resetaccumulators", "label": "resetAccumulators", "file_type": "code", "source_file": "ANN/ANN_CoreCPU.hpp", "source_location": "L35"}, {"id": "ann_ann_corecpu_corecpu_update", "label": "update", "file_type": "code", "source_file": "ANN/ANN_CoreCPU.hpp", "source_location": "L36"}, {"id": "unique_ptr", "label": "unique_ptr", "file_type": "code", "source_file": "ANN/ANN_CoreCPU.hpp", "source_location": "L40"}, {"id": "corecpuworker", "label": "CoreCPUWorker", "file_type": "code", "source_file": "ANN/ANN_CoreCPU.hpp", "source_location": "L40"}, {"id": "t", "label": "T", "file_type": "code", "source_file": "ANN/ANN_CoreCPU.hpp", "source_location": "L40"}, {"id": "ann_ann_corecpu_corecpu_stepworker", "label": "stepWorker", "file_type": "code", "source_file": "ANN/ANN_CoreCPU.hpp", "source_location": "L40"}, {"id": "qthreadpool", "label": "QThreadPool", "file_type": "code", "source_file": "ANN/ANN_CoreCPU.hpp", "source_location": "L49"}, {"id": "ann_ann_corecpu_corecpu_workerpool", "label": "workerPool", "file_type": "code", "source_file": "ANN/ANN_CoreCPU.hpp", "source_location": "L49"}, {"id": "tensor3d", "label": "Tensor3D", "file_type": "code", "source_file": "ANN/ANN_CoreCPU.hpp", "source_location": "L52"}, {"id": "ann_ann_corecpu_corecpu_accum_dcost_dweights", "label": "accum_dCost_dWeights", "file_type": "code", "source_file": "ANN/ANN_CoreCPU.hpp", "source_location": "L52"}, {"id": "tensor2d", "label": "Tensor2D", "file_type": "code", "source_file": "ANN/ANN_CoreCPU.hpp", "source_location": "L53"}, {"id": "ann_ann_corecpu_corecpu_accum_dcost_dbiases", "label": "accum_dCost_dBiases", "file_type": "code", "source_file": "ANN/ANN_CoreCPU.hpp", "source_location": "L53"}, {"id": "qmutex", "label": "QMutex", "file_type": "code", "source_file": "ANN/ANN_CoreCPU.hpp", "source_location": "L54"}, {"id": "ann_ann_corecpu_corecpu_accumulatormutex", "label": "accumulatorMutex", "file_type": "code", "source_file": "ANN/ANN_CoreCPU.hpp", "source_location": "L54"}, {"id": "ann_ann_corecpu_corecpu_adam_m_weights", "label": "adam_m_weights", "file_type": "code", "source_file": "ANN/ANN_CoreCPU.hpp", "source_location": "L57"}, {"id": "ann_ann_corecpu_corecpu_adam_m_biases", "label": "adam_m_biases", "file_type": "code", "source_file": "ANN/ANN_CoreCPU.hpp", "source_location": "L58"}, {"id": "ann_ann_corecpu_corecpu_adam_v_weights", "label": "adam_v_weights", "file_type": "code", "source_file": "ANN/ANN_CoreCPU.hpp", "source_location": "L59"}, {"id": "ann_ann_corecpu_corecpu_adam_v_biases", "label": "adam_v_biases", "file_type": "code", "source_file": "ANN/ANN_CoreCPU.hpp", "source_location": "L60"}, {"id": "ulong", "label": "ulong", "file_type": "code", "source_file": "ANN/ANN_CoreCPU.hpp", "source_location": "L61"}, {"id": "ann_ann_corecpu_corecpu_adam_t", "label": "adam_t", "file_type": "code", "source_file": "ANN/ANN_CoreCPU.hpp", "source_location": "L61"}, {"id": "ann_ann_corecpu_corecpu_initializeparameters", "label": "initializeParameters", "file_type": "code", "source_file": "ANN/ANN_CoreCPU.hpp", "source_location": "L64"}, {"id": "ann_ann_corecpu_corecpu_allocateglobalaccumulators", "label": "allocateGlobalAccumulators", "file_type": "code", "source_file": "ANN/ANN_CoreCPU.hpp", "source_location": "L65"}, {"id": "ann_ann_corecpu_corecpu_allocateadamstate", "label": "allocateAdamState", "file_type": "code", "source_file": "ANN/ANN_CoreCPU.hpp", "source_location": "L66"}, {"id": "ann_ann_corecpu_corecpu_runworkers", "label": "runWorkers", "file_type": "code", "source_file": "ANN/ANN_CoreCPU.hpp", "source_location": "L73"}, {"id": "ann_ann_corecpu_corecpu_resetglobalaccumulators", "label": "resetGlobalAccumulators", "file_type": "code", "source_file": "ANN/ANN_CoreCPU.hpp", "source_location": "L76"}, {"id": "ann_ann_corecpu_corecpu_mergeworkeraccumulators", "label": "mergeWorkerAccumulators", "file_type": "code", "source_file": "ANN/ANN_CoreCPU.hpp", "source_location": "L77"}, {"id": "ann_ann_corecpu_corecpu_reportprogress", "label": "reportProgress", "file_type": "code", "source_file": "ANN/ANN_CoreCPU.hpp", "source_location": "L78"}], "edges": [{"source": "home_naschpitz_projects_nn_ann_ann_corecpu_hpp", "target": "home_naschpitz_projects_nn_ann_ann_core_hpp", "relation": "imports", "context": "import", "confidence": "EXTRACTED", "source_file": "ANN/ANN_CoreCPU.hpp", "source_location": "L4", "weight": 1.0}, {"source": "home_naschpitz_projects_nn_ann_ann_corecpu_hpp", "target": "home_naschpitz_projects_nn_ann_ann_corecpuworker_hpp", "relation": "imports", "context": "import", "confidence": "EXTRACTED", "source_file": "ANN/ANN_CoreCPU.hpp", "source_location": "L5", "weight": 1.0}, {"source": "home_naschpitz_projects_nn_ann_ann_corecpu_hpp", "target": "qmutex", "relation": "imports", "context": "import", "confidence": "EXTRACTED", "source_file": "ANN/ANN_CoreCPU.hpp", "source_location": "L7", "weight": 1.0}, {"source": "home_naschpitz_projects_nn_ann_ann_corecpu_hpp", "target": "qthreadpool", "relation": "imports", "context": "import", "confidence": "EXTRACTED", "source_file": "ANN/ANN_CoreCPU.hpp", "source_location": "L8", "weight": 1.0}, {"source": "home_naschpitz_projects_nn_ann_ann_corecpu_hpp", "target": "functional", "relation": "imports", "context": "import", "confidence": "EXTRACTED", "source_file": "ANN/ANN_CoreCPU.hpp", "source_location": "L10", "weight": 1.0}, {"source": "home_naschpitz_projects_nn_ann_ann_corecpu_hpp", "target": "memory", "relation": "imports", "context": "import", "confidence": "EXTRACTED", "source_file": "ANN/ANN_CoreCPU.hpp", "source_location": "L11", "weight": 1.0}, {"source": "home_naschpitz_projects_nn_ann_ann_corecpu_hpp", "target": "vector", "relation": "imports", "context": "import", "confidence": "EXTRACTED", "source_file": "ANN/ANN_CoreCPU.hpp", "source_location": "L12", "weight": 1.0}, {"source": "home_naschpitz_projects_nn_ann_ann_corecpu_hpp", "target": "ann_ann_corecpu_corecpu", "relation": "contains", "confidence": "EXTRACTED", "source_file": "ANN/ANN_CoreCPU.hpp", "source_location": "L20", "weight": 1.0}, {"source": "ann_ann_corecpu_corecpu", "target": "core", "relation": "inherits", "confidence": "EXTRACTED", "source_file": "ANN/ANN_CoreCPU.hpp", "source_location": "L20", "weight": 1.0}, {"source": "ann_ann_corecpu_corecpu", "target": "ann_ann_corecpu_corecpu_predict", "relation": "defines", "confidence": "EXTRACTED", "source_file": "ANN/ANN_CoreCPU.hpp", "source_location": "L27", "weight": 1.0, "context": "field"}, {"source": "ann_ann_corecpu_corecpu", "target": "ann_ann_corecpu_corecpu_predict", "relation": "defines", "confidence": "EXTRACTED", "source_file": "ANN/ANN_CoreCPU.hpp", "source_location": "L28", "weight": 1.0, "context": "field"}, {"source": "ann_ann_corecpu_corecpu", "target": "ann_ann_corecpu_corecpu_train", "relation": "defines", "confidence": "EXTRACTED", "source_file": "ANN/ANN_CoreCPU.hpp", "source_location": "L29", "weight": 1.0, "context": "field"}, {"source": "ann_ann_corecpu_corecpu", "target": "ann_ann_corecpu_corecpu_test", "relation": "defines", "confidence": "EXTRACTED", "source_file": "ANN/ANN_CoreCPU.hpp", "source_location": "L30", "weight": 1.0, "context": "field"}, {"source": "ann_ann_corecpu_corecpu", "target": "ann_ann_corecpu_corecpu_backpropagate", "relation": "defines", "confidence": "EXTRACTED", "source_file": "ANN/ANN_CoreCPU.hpp", "source_location": "L33", "weight": 1.0, "context": "field"}, {"source": "ann_ann_corecpu_corecpu", "target": "ann_ann_corecpu_corecpu_accumulate", "relation": "defines", "confidence": "EXTRACTED", "source_file": "ANN/ANN_CoreCPU.hpp", "source_location": "L34", "weight": 1.0, "context": "field"}, {"source": "ann_ann_corecpu_corecpu", "target": "ann_ann_corecpu_corecpu_resetaccumulators", "relation": "defines", "confidence": "EXTRACTED", "source_file": "ANN/ANN_CoreCPU.hpp", "source_location": "L35", "weight": 1.0, "context": "field"}, {"source": "ann_ann_corecpu_corecpu", "target": "ann_ann_corecpu_corecpu_update", "relation": "defines", "confidence": "EXTRACTED", "source_file": "ANN/ANN_CoreCPU.hpp", "source_location": "L36", "weight": 1.0, "context": "field"}, {"source": "ann_ann_corecpu_corecpu", "target": "unique_ptr", "relation": "references", "confidence": "EXTRACTED", "source_file": "ANN/ANN_CoreCPU.hpp", "source_location": "L40", "weight": 1.0, "context": "field"}, {"source": "ann_ann_corecpu_corecpu", "target": "corecpuworker", "relation": "references", "confidence": "EXTRACTED", "source_file": "ANN/ANN_CoreCPU.hpp", "source_location": "L40", "weight": 1.0, "context": "generic_arg"}, {"source": "ann_ann_corecpu_corecpu", "target": "t", "relation": "references", "confidence": "EXTRACTED", "source_file": "ANN/ANN_CoreCPU.hpp", "source_location": "L40", "weight": 1.0, "context": "generic_arg"}, {"source": "ann_ann_corecpu_corecpu", "target": "ann_ann_corecpu_corecpu_stepworker", "relation": "defines", "confidence": "EXTRACTED", "source_file": "ANN/ANN_CoreCPU.hpp", "source_location": "L40", "weight": 1.0, "context": "field"}, {"source": "ann_ann_corecpu_corecpu", "target": "qthreadpool", "relation": "references", "confidence": "EXTRACTED", "source_file": "ANN/ANN_CoreCPU.hpp", "source_location": "L49", "weight": 1.0, "context": "field"}, {"source": "ann_ann_corecpu_corecpu", "target": "ann_ann_corecpu_corecpu_workerpool", "relation": "defines", "confidence": "EXTRACTED", "source_file": "ANN/ANN_CoreCPU.hpp", "source_location": "L49", "weight": 1.0, "context": "field"}, {"source": "ann_ann_corecpu_corecpu", "target": "tensor3d", "relation": "references", "confidence": "EXTRACTED", "source_file": "ANN/ANN_CoreCPU.hpp", "source_location": "L52", "weight": 1.0, "context": "field"}, {"source": "ann_ann_corecpu_corecpu", "target": "t", "relation": "references", "confidence": "EXTRACTED", "source_file": "ANN/ANN_CoreCPU.hpp", "source_location": "L52", "weight": 1.0, "context": "generic_arg"}, {"source": "ann_ann_corecpu_corecpu", "target": "ann_ann_corecpu_corecpu_accum_dcost_dweights", "relation": "defines", "confidence": "EXTRACTED", "source_file": "ANN/ANN_CoreCPU.hpp", "source_location": "L52", "weight": 1.0, "context": "field"}, {"source": "ann_ann_corecpu_corecpu", "target": "tensor2d", "relation": "references", "confidence": "EXTRACTED", "source_file": "ANN/ANN_CoreCPU.hpp", "source_location": "L53", "weight": 1.0, "context": "field"}, {"source": "ann_ann_corecpu_corecpu", "target": "t", "relation": "references", "confidence": "EXTRACTED", "source_file": "ANN/ANN_CoreCPU.hpp", "source_location": "L53", "weight": 1.0, "context": "generic_arg"}, {"source": "ann_ann_corecpu_corecpu", "target": "ann_ann_corecpu_corecpu_accum_dcost_dbiases", "relation": "defines", "confidence": "EXTRACTED", "source_file": "ANN/ANN_CoreCPU.hpp", "source_location": "L53", "weight": 1.0, "context": "field"}, {"source": "ann_ann_corecpu_corecpu", "target": "qmutex", "relation": "references", "confidence": "EXTRACTED", "source_file": "ANN/ANN_CoreCPU.hpp", "source_location": "L54", "weight": 1.0, "context": "field"}, {"source": "ann_ann_corecpu_corecpu", "target": "ann_ann_corecpu_corecpu_accumulatormutex", "relation": "defines", "confidence": "EXTRACTED", "source_file": "ANN/ANN_CoreCPU.hpp", "source_location": "L54", "weight": 1.0, "context": "field"}, {"source": "ann_ann_corecpu_corecpu", "target": "tensor3d", "relation": "references", "confidence": "EXTRACTED", "source_file": "ANN/ANN_CoreCPU.hpp", "source_location": "L57", "weight": 1.0, "context": "field"}, {"source": "ann_ann_corecpu_corecpu", "target": "t", "relation": "references", "confidence": "EXTRACTED", "source_file": "ANN/ANN_CoreCPU.hpp", "source_location": "L57", "weight": 1.0, "context": "generic_arg"}, {"source": "ann_ann_corecpu_corecpu", "target": "ann_ann_corecpu_corecpu_adam_m_weights", "relation": "defines", "confidence": "EXTRACTED", "source_file": "ANN/ANN_CoreCPU.hpp", "source_location": "L57", "weight": 1.0, "context": "field"}, {"source": "ann_ann_corecpu_corecpu", "target": "tensor2d", "relation": "references", "confidence": "EXTRACTED", "source_file": "ANN/ANN_CoreCPU.hpp", "source_location": "L58", "weight": 1.0, "context": "field"}, {"source": "ann_ann_corecpu_corecpu", "target": "t", "relation": "references", "confidence": "EXTRACTED", "source_file": "ANN/ANN_CoreCPU.hpp", "source_location": "L58", "weight": 1.0, "context": "generic_arg"}, {"source": "ann_ann_corecpu_corecpu", "target": "ann_ann_corecpu_corecpu_adam_m_biases", "relation": "defines", "confidence": "EXTRACTED", "source_file": "ANN/ANN_CoreCPU.hpp", "source_location": "L58", "weight": 1.0, "context": "field"}, {"source": "ann_ann_corecpu_corecpu", "target": "tensor3d", "relation": "references", "confidence": "EXTRACTED", "source_file": "ANN/ANN_CoreCPU.hpp", "source_location": "L59", "weight": 1.0, "context": "field"}, {"source": "ann_ann_corecpu_corecpu", "target": "t", "relation": "references", "confidence": "EXTRACTED", "source_file": "ANN/ANN_CoreCPU.hpp", "source_location": "L59", "weight": 1.0, "context": "generic_arg"}, {"source": "ann_ann_corecpu_corecpu", "target": "ann_ann_corecpu_corecpu_adam_v_weights", "relation": "defines", "confidence": "EXTRACTED", "source_file": "ANN/ANN_CoreCPU.hpp", "source_location": "L59", "weight": 1.0, "context": "field"}, {"source": "ann_ann_corecpu_corecpu", "target": "tensor2d", "relation": "references", "confidence": "EXTRACTED", "source_file": "ANN/ANN_CoreCPU.hpp", "source_location": "L60", "weight": 1.0, "context": "field"}, {"source": "ann_ann_corecpu_corecpu", "target": "t", "relation": "references", "confidence": "EXTRACTED", "source_file": "ANN/ANN_CoreCPU.hpp", "source_location": "L60", "weight": 1.0, "context": "generic_arg"}, {"source": "ann_ann_corecpu_corecpu", "target": "ann_ann_corecpu_corecpu_adam_v_biases", "relation": "defines", "confidence": "EXTRACTED", "source_file": "ANN/ANN_CoreCPU.hpp", "source_location": "L60", "weight": 1.0, "context": "field"}, {"source": "ann_ann_corecpu_corecpu", "target": "ulong", "relation": "references", "confidence": "EXTRACTED", "source_file": "ANN/ANN_CoreCPU.hpp", "source_location": "L61", "weight": 1.0, "context": "field"}, {"source": "ann_ann_corecpu_corecpu", "target": "ann_ann_corecpu_corecpu_adam_t", "relation": "defines", "confidence": "EXTRACTED", "source_file": "ANN/ANN_CoreCPU.hpp", "source_location": "L61", "weight": 1.0, "context": "field"}, {"source": "ann_ann_corecpu_corecpu", "target": "ann_ann_corecpu_corecpu_initializeparameters", "relation": "defines", "confidence": "EXTRACTED", "source_file": "ANN/ANN_CoreCPU.hpp", "source_location": "L64", "weight": 1.0, "context": "field"}, {"source": "ann_ann_corecpu_corecpu", "target": "ann_ann_corecpu_corecpu_allocateglobalaccumulators", "relation": "defines", "confidence": "EXTRACTED", "source_file": "ANN/ANN_CoreCPU.hpp", "source_location": "L65", "weight": 1.0, "context": "field"}, {"source": "ann_ann_corecpu_corecpu", "target": "ann_ann_corecpu_corecpu_allocateadamstate", "relation": "defines", "confidence": "EXTRACTED", "source_file": "ANN/ANN_CoreCPU.hpp", "source_location": "L66", "weight": 1.0, "context": "field"}, {"source": "ann_ann_corecpu_corecpu", "target": "ann_ann_corecpu_corecpu_runworkers", "relation": "defines", "confidence": "EXTRACTED", "source_file": "ANN/ANN_CoreCPU.hpp", "source_location": "L73", "weight": 1.0, "context": "field"}, {"source": "ann_ann_corecpu_corecpu", "target": "ann_ann_corecpu_corecpu_resetglobalaccumulators", "relation": "defines", "confidence": "EXTRACTED", "source_file": "ANN/ANN_CoreCPU.hpp", "source_location": "L76", "weight": 1.0, "context": "field"}, {"source": "ann_ann_corecpu_corecpu", "target": "ann_ann_corecpu_corecpu_mergeworkeraccumulators", "relation": "defines", "confidence": "EXTRACTED", "source_file": "ANN/ANN_CoreCPU.hpp", "source_location": "L77", "weight": 1.0, "context": "field"}, {"source": "ann_ann_corecpu_corecpu", "target": "ann_ann_corecpu_corecpu_reportprogress", "relation": "defines", "confidence": "EXTRACTED", "source_file": "ANN/ANN_CoreCPU.hpp", "source_location": "L78", "weight": 1.0, "context": "field"}], "raw_calls": []}